calculadorapnav/__init__.py
calculadorapnav/_version.py
calculadorapnav/emissions_tracker.py
calculadorapnav/input.py
calculadorapnav/lock.py
calculadorapnav/output.py
calculadorapnav/core/__init__.py
calculadorapnav/core/cloud.py
calculadorapnav/core/config.py
calculadorapnav/core/cpu.py
calculadorapnav/core/emissions.py
calculadorapnav/core/gpu.py
calculadorapnav/core/input_validation.py
calculadorapnav/core/model_data.py
calculadorapnav/core/powermetrics.py
calculadorapnav/core/rapl.py
calculadorapnav/core/resource_tracker.py
calculadorapnav/core/schemas.py
calculadorapnav/core/units.py
calculadorapnav/core/util.py
calculadorapnav/data/canada_provinces.geojson
calculadorapnav/data/assets/flow_calculator.jpg
calculadorapnav/data/assets/foot_pnav.jpg
calculadorapnav/data/assets/logo_pnav.png
calculadorapnav/data/cloud/impact.csv
calculadorapnav/data/hardware/cpu_power.csv
calculadorapnav/data/private_infra/2023-07-07-22-40-48.png
calculadorapnav/data/private_infra/carbon_intensity_per_source.json
calculadorapnav/data/private_infra/global_energy_mix.json
calculadorapnav/data/private_infra/our_world_in_data.ipynb
calculadorapnav/data/private_infra/world_energy_mix.csv
calculadorapnav/data/private_infra/2016/canada_energy_mix.json
calculadorapnav/data/private_infra/2016/global_energy_mix-old.json
calculadorapnav/data/private_infra/2016/usa_emissions.json
calculadorapnav/data/private_infra/2020/01_get_world_carbon_intensity.ipynb
calculadorapnav/data/private_infra/2020/02_convert_csv_to_json.ipynb
calculadorapnav/data/private_infra/2020/03_add_eu_data.ipynb
calculadorapnav/data/private_infra/2020/eu-carbon-intensity-electricity.csv
calculadorapnav/external/__init__.py
calculadorapnav/external/geography.py
calculadorapnav/external/hardware.py
calculadorapnav/external/logger.py
calculadorapnav/external/scheduler.py
calculadorapnav/external/task.py
calculadorapnav/output_methods/__init__.py
calculadorapnav/output_methods/base_output.py
calculadorapnav-1.0.2.dist-info/licenses/LICENSE
calculadorapnav-1.0.2.dist-info/METADATA
calculadorapnav-1.0.2.dist-info/WHEEL
calculadorapnav-1.0.2.dist-info/top_level.txt
calculadorapnav-1.0.2.dist-info/RECORD
