Metadata-Version: 2.4
Name: calculadorapnav
Version: 1.0.2
Summary: Una librería para cálculos de CO2
Home-page: 
Author: PNAV
Author-email: tu.email@example.com
License: MIT
Classifier: Development Status :: 3 - Alpha
Classifier: Intended Audience :: Developers
Classifier: Natural Language :: Spanish
Classifier: Programming Language :: Python :: 3
Classifier: Programming Language :: Python :: 3.9
Classifier: Programming Language :: Python :: 3.10
Classifier: Programming Language :: Python :: 3.11
Classifier: Programming Language :: Python :: 3.12
Requires-Python: >=3.9,<3.13
License-File: LICENSE
Requires-Dist: arrow<2.0,>=1.2.3
Requires-Dist: click<9.0,>=8.0
Requires-Dist: fief-client[cli]<1.0,>=0.9
Requires-Dist: pandas<2.0,>=1.5.0
Requires-Dist: numpy<2.0,>=1.25
Requires-Dist: psutil<6.0,>=5.8
Requires-Dist: py-cpuinfo<8.0,>=7.0
Requires-Dist: pydantic<2.11.5,>=1.8
Requires-Dist: pynvml<12.0,>=11.0
Requires-Dist: rapidfuzz<3.11.0,>=1.7
Requires-Dist: requests<3.0,>=2.25
Requires-Dist: questionary<2.0,>=1.10
Requires-Dist: rich<13.0,>=10.0
Requires-Dist: typer<1.0,>=0.4
Requires-Dist: tensorflow<2.19,>=2.6
Requires-Dist: torch<=2.7.1,>=1.10
Requires-Dist: protobuf<3.21,>=3.20.0
Provides-Extra: dev
Requires-Dist: pytest; extra == "dev"
Requires-Dist: coverage; extra == "dev"
Dynamic: author
Dynamic: author-email
Dynamic: classifier
Dynamic: description
Dynamic: description-content-type
Dynamic: license
Dynamic: license-file
Dynamic: provides-extra
Dynamic: requires-dist
Dynamic: requires-python
Dynamic: summary
